odoo/addons/account_invoice_blocking/README.rst
odoo/addons/account_invoice_blocking/__init__.py
odoo/addons/account_invoice_blocking/__manifest__.py
odoo/addons/account_invoice_blocking/i18n/account_invoice_blocking.pot
odoo/addons/account_invoice_blocking/i18n/de.po
odoo/addons/account_invoice_blocking/i18n/nl.po
odoo/addons/account_invoice_blocking/models/__init__.py
odoo/addons/account_invoice_blocking/models/account_invoice.py
odoo/addons/account_invoice_blocking/static/description/icon.png
odoo/addons/account_invoice_blocking/tests/__init__.py
odoo/addons/account_invoice_blocking/tests/test_account_invoice_blocking.py
odoo/addons/account_invoice_blocking/views/account_invoice.xml
odoo11_addon_account_invoice_blocking-11.0.1.0.0.99.dev5.dist-info/METADATA
odoo11_addon_account_invoice_blocking-11.0.1.0.0.99.dev5.dist-info/RECORD
odoo11_addon_account_invoice_blocking-11.0.1.0.0.99.dev5.dist-info/WHEEL
odoo11_addon_account_invoice_blocking-11.0.1.0.0.99.dev5.dist-info/top_level.txt
